fa_explorer/__init__.py
fa_explorer/fa_explorer.py
fa_explorer-0.0.1.dist-info/METADATA
fa_explorer-0.0.1.dist-info/WHEEL
fa_explorer-0.0.1.dist-info/licenses/LICENSE
fa_explorer-0.0.1.dist-info/RECORD
